blackbench/__init__.py
blackbench/__main__.py
blackbench/resources.py
blackbench/utils.py
blackbench/micro-targets/comments.py
blackbench/micro-targets/dict-literal.py
blackbench/micro-targets/list-literal.py
blackbench/micro-targets/nested.py
blackbench/micro-targets/strings-list.py
blackbench/misc/dummy-benchmark.py
blackbench/normal-targets/black/LICENSE
blackbench/normal-targets/black/__init__.py
blackbench/normal-targets/black/brackets.py
blackbench/normal-targets/black/comments.py
blackbench/normal-targets/black/linegen.py
blackbench/normal-targets/black/lines.py
blackbench/normal-targets/black/mode.py
blackbench/normal-targets/black/nodes.py
blackbench/normal-targets/black/output.py
blackbench/normal-targets/black/strings.py
blackbench/normal-targets/flit/LICENSE
blackbench/normal-targets/flit/install.py
blackbench/normal-targets/flit/sdist.py
blackbench/normal-targets/flit_core/LICENSE
blackbench/normal-targets/flit_core/config.py
blackbench/task-templates/format-fast-template.py
blackbench/task-templates/format-template.py
blackbench/task-templates/parse-template.py
blackbench-21.8a2.dist-info/entry_points.txt
blackbench-21.8a2.dist-info/LICENSE.txt
blackbench-21.8a2.dist-info/WHEEL
blackbench-21.8a2.dist-info/METADATA
blackbench-21.8a2.dist-info/RECORD
