Metadata-Version: 2.1
Name: blackbench
Version: 21.8a2
Summary: A benchmarking suite for Black, the Python code formatter.
Home-page: https://github.com/ichard26/blackbench
Author: Richard Si
Author-email: 63936253+ichard26@users.noreply.github.com
Requires-Python: >=3.8
Classifier: Development Status :: 3 - Alpha
Classifier: License :: OSI Approved :: MIT License
Classifier: Programming Language :: Python :: Implementation :: CPython
Classifier: Programming Language :: Python :: 3 :: Only
Classifier: Programming Language :: Python :: 3.8
Classifier: Programming Language :: Python :: 3.9
Classifier: Intended Audience :: Developers
Classifier: Topic :: Software Development :: Testing
Classifier: Typing :: Typed
Requires-Dist: click >= 8.0.0
Requires-Dist: cloup >= 0.9.0
Requires-Dist: pyperf >= 2.0.0, <3
Project-URL: Changelog, https://blackbench.readthedocs.io/en/latest/changelog.html
Project-URL: Documentation, https://blackbench.readthedocs.io/en/stable/
